tfmini/__init__.py
tfmini/tfmini.py
tfmini-0.3.2.dist-info/LICENSE
tfmini-0.3.2.dist-info/WHEEL
tfmini-0.3.2.dist-info/METADATA
tfmini-0.3.2.dist-info/RECORD
