Metadata-Version: 2.1
Name: tfmini
Version: 0.3.2
Summary: A driver for the TFmini LiDAR sold by Sparkfun
Home-page: https://pypi.org/project/tfmini/
License: MIT
Keywords: robot,pi,serial,sensor,range,ranging,robotics,tf
Author: walchko
Author-email: walchko@users.noreply.github.com
Requires-Python: >=3.6
Classifier: Development Status :: 4 - Beta
Classifier: Intended Audience :: Developers
Classifier: License :: OSI Approved :: MIT License
Classifier: Operating System :: OS Independent
Classifier: Programming Language :: Python :: 3
Classifier: Programming Language :: Python :: 3.6
Classifier: Programming Language :: Python :: 3.7
Classifier: Programming Language :: Python :: 3.8
Classifier: Programming Language :: Python :: 3.9
Classifier: Topic :: Software Development :: Libraries
Classifier: Topic :: Software Development :: Libraries :: Application Frameworks
Classifier: Topic :: Software Development :: Libraries :: Python Modules
Requires-Dist: importlib-metadata; python_version < "3.8"
Requires-Dist: pyserial
Project-URL: Repository, http://github.com/MomsFriendlyRobotCompany/tfmini
